<?xml version="1.0" encoding="UTF-8"?>
<product>
	<esb>
		<Cluster name="wso2esb-1">
			<Domain>wso2.carbon.domain.as2</Domain>
			<Offset>27</Offset>
			<readOnly>false</readOnly>
			<targetPath>/_system/esb1</targetPath>
			<Database>
				<currentDBConfig>oracle-esb1</currentDBConfig>
				<dbConfigname>oracle-esb1</dbConfigname>
				<url>jdbc:oracle:thin:dharshana/dharshana2@10.100.3.104:1521:orcl</url>
				<userName>dharshana</userName>
				<password>dharshana</password>
				<driverName>oracle.jdbc.driver.OracleDriver</driverName>
				<maxActive>5</maxActive>
				<maxWait>60000</maxWait>
				<minIdle>50</minIdle>
				<validationQuery>SELECT 1 FROM DUAL</validationQuery>
			</Database>
		</Cluster>
		<Cluster name="wso2esb-2">
			<Domain>wso2.carbon.domain.as2</Domain>
			<Offset>28</Offset>
			<readOnly>true</readOnly>
			<targetPath>/_system/esb2</targetPath>
			<Database>
				<currentDBConfig>oracle-esb2</currentDBConfig>
				<dbConfigname>oracle-esb2</dbConfigname>
				<url>jdbc:oracle:thin:dharshana/dharshana2@10.100.3.104:1521:orcl</url>
				<userName>dharshana</userName>
				<password>dharshana</password>
				<driverName>oracle.jdbc.driver.OracleDriver</driverName>
				<maxActive>5</maxActive>
				<maxWait>60000</maxWait>
				<minIdle>50</minIdle>
				<validationQuery>SELECT 1 FROM DUAL</validationQuery>
			</Database>
		</Cluster>
	</esb>
	<appServer>
		<Cluster name="wso2as-1">
			<Domain>wso2.carbon.domain.as2</Domain>
			<Offset>27</Offset>
			<readOnly>false</readOnly>
			<targetPath>/_system/as1</targetPath>
			<Database>
				<currentDBConfig>oracle-as1</currentDBConfig>
				<dbConfigname>oracle-esb1</dbConfigname>
				<url>jdbc:oracle:thin:dharshana/dharshana2@10.100.3.104:1521:orcl</url>
				<userName>dharshana</userName>
				<password>dharshana</password>
				<driverName>oracle.jdbc.driver.OracleDriver</driverName>
				<maxActive>5</maxActive>
				<maxWait>60000</maxWait>
				<minIdle>50</minIdle>
				<validationQuery>SELECT 1 FROM DUAL</validationQuery>
			</Database>
		</Cluster>
		<Cluster name="wso2as-2">
			<Domain>wso2.carbon.domain.as2</Domain>
			<Offset>28</Offset>
			<readOnly>true</readOnly>
			<targetPath>/_system/as2</targetPath>
			<Database>
				<currentDBConfig>oracle-as2</currentDBConfig>
				<dbConfigname>oracle-as2</dbConfigname>
				<url>jdbc:oracle:thin:dharshana/dharshana2@10.100.3.104:1521:orcl</url>
				<userName>dharshana</userName>
				<password>dharshana</password>
				<driverName>oracle.jdbc.driver.OracleDriver</driverName>
				<maxActive>5</maxActive>
				<maxWait>60000</maxWait>
				<minIdle>50</minIdle>
				<validationQuery>SELECT 1 FROM DUAL</validationQuery>
			</Database>
		</Cluster>
	</appServer>
</product>